aiohttp_aws_auth/__init__.py
aiohttp_aws_auth/py.typed
aiohttp_aws_auth-0.0.3.dist-info/WHEEL
aiohttp_aws_auth-0.0.3.dist-info/METADATA
aiohttp_aws_auth-0.0.3.dist-info/RECORD
