Metadata-Version: 2.3
Name: aiohttp-aws-auth
Version: 0.0.3
Summary: Provides AWS authentication middlewares to be used with aiohttp
Author: Jakub Jantosik
Author-email: Jakub Jantosik <jakub.jantosik@gmail.com>
Classifier: Programming Language :: Python
Classifier: Programming Language :: Python :: 3
Classifier: Programming Language :: Python :: 3 :: Only
Classifier: Programming Language :: Python :: 3.10
Classifier: Programming Language :: Python :: 3.11
Classifier: Programming Language :: Python :: 3.12
Classifier: Programming Language :: Python :: 3.13
Classifier: Programming Language :: Python :: 3.14
Classifier: Intended Audience :: Developers
Classifier: Intended Audience :: Information Technology
Classifier: Operating System :: OS Independent
Classifier: Topic :: Software Development :: Libraries :: Python Modules
Classifier: Topic :: Internet
Requires-Dist: aiohttp>=3.12.0
Requires-Python: >=3.10
